cobo_waas2/__init__.py
cobo_waas2/api_client.py
cobo_waas2/api_response.py
cobo_waas2/configuration.py
cobo_waas2/exceptions.py
cobo_waas2/py.typed
cobo_waas2/rest.py
cobo_waas2/server_demo.py
cobo_waas2/api/__init__.py
cobo_waas2/api/address_books_api.py
cobo_waas2/api/app_workflows_api.py
cobo_waas2/api/auto_sweep_api.py
cobo_waas2/api/compliance_api.py
cobo_waas2/api/developers_api.py
cobo_waas2/api/developers_webhooks_api.py
cobo_waas2/api/fee_station_api.py
cobo_waas2/api/graph_ql_api.py
cobo_waas2/api/o_auth_api.py
cobo_waas2/api/organizations_api.py
cobo_waas2/api/payment_api.py
cobo_waas2/api/prime_broker_api.py
cobo_waas2/api/stakings_api.py
cobo_waas2/api/swaps_api.py
cobo_waas2/api/tokenization_api.py
cobo_waas2/api/transactions_api.py
cobo_waas2/api/travel_rule_api.py
cobo_waas2/api/wallets_api.py
cobo_waas2/api/wallets_exchange_wallet_api.py
cobo_waas2/api/wallets_mpc_wallets_api.py
cobo_waas2/api/wallets_smart_contract_wallets_api.py
cobo_waas2/crypto/__init__.py
cobo_waas2/crypto/local_ed25519_signer.py
cobo_waas2/crypto/local_secp256k1_signer.py
cobo_waas2/crypto/signer.py
cobo_waas2/crypto/signing_helper.py
cobo_waas2/models/__init__.py
cobo_waas2/models/account.py
cobo_waas2/models/acquiring_type.py
cobo_waas2/models/activity.py
cobo_waas2/models/activity_action.py
cobo_waas2/models/activity_extra.py
cobo_waas2/models/activity_initiator.py
cobo_waas2/models/activity_status.py
cobo_waas2/models/activity_timeline.py
cobo_waas2/models/activity_type.py
cobo_waas2/models/address_balance.py
cobo_waas2/models/address_book.py
cobo_waas2/models/address_encoding.py
cobo_waas2/models/address_info.py
cobo_waas2/models/address_risk_level.py
cobo_waas2/models/address_transfer_destination.py
cobo_waas2/models/address_transfer_destination_account_output.py
cobo_waas2/models/address_transfer_destination_utxo_outputs_inner.py
cobo_waas2/models/addresses_event_data.py
cobo_waas2/models/addresses_event_data_all_of_addresses.py
cobo_waas2/models/allocation_item.py
cobo_waas2-1.30.0.dist-info/METADATA
cobo_waas2-1.30.0.dist-info/WHEEL
cobo_waas2-1.30.0.dist-info/top_level.txt
cobo_waas2-1.30.0.dist-info/RECORD
