Metadata-Version: 2.1
Name: cobo-waas2
Version: 1.30.0
Summary: Cobo Wallet as a Service 2.0
Home-page: https://github.com/CoboGlobal/cobo-waas2-python-sdk
Author: Cobo WaaS
Author-email: help@cobo.com
License: Apache 2.0
Keywords: OpenAPI,OpenAPI-Generator,Cobo Wallet as a Service 2.0
Platform: UNKNOWN
Requires-Dist: urllib3>=2.6.0
Requires-Dist: python-dateutil
Requires-Dist: pydantic>=2
Requires-Dist: typing-extensions>=4.7.1
Requires-Dist: PyNaCl==1.5.0
Requires-Dist: ecdsa==0.19.0
Requires-Dist: fastapi>=0.103.2
Requires-Dist: uvicorn==0.22.0
